sentencepiece/__init__.py
sentencepiece/_sentencepiece.cp312-win32.pyd
sentencepiece/_version.py
sentencepiece/sentencepiece_model_pb2.py
sentencepiece/sentencepiece_pb2.py
sentencepiece-0.2.0.dist-info/METADATA
sentencepiece-0.2.0.dist-info/WHEEL
sentencepiece-0.2.0.dist-info/top_level.txt
sentencepiece-0.2.0.dist-info/RECORD
