Metadata-Version: 2.1
Name: sentencepiece
Version: 0.2.0
Summary: SentencePiece python wrapper
Home-page: https://github.com/google/sentencepiece
Author: Taku Kudo
Author-email: taku@google.com
License: Apache
Platform: Unix
Classifier: Development Status :: 5 - Production/Stable
Classifier: Environment :: Console
Classifier: Intended Audience :: Developers
Classifier: Intended Audience :: Science/Research
Classifier: License :: OSI Approved :: Apache Software License
Classifier: Operating System :: Unix
Classifier: Programming Language :: Python
Classifier: Topic :: Text Processing :: Linguistic
Classifier: Topic :: Software Development :: Libraries :: Python Modules
